README.txt
setup.cfg
setup.py
docs/HISTORY.txt
docs/INSTALL.txt
docs/LICENSE.GPL
docs/LICENSE.txt
opsuite/__init__.py
opsuite.config.egg-info/PKG-INFO
opsuite.config.egg-info/SOURCES.txt
opsuite.config.egg-info/dependency_links.txt
opsuite.config.egg-info/entry_points.txt
opsuite.config.egg-info/namespace_packages.txt
opsuite.config.egg-info/not-zip-safe
opsuite.config.egg-info/paster_plugins.txt
opsuite.config.egg-info/requires.txt
opsuite.config.egg-info/top_level.txt
opsuite/config/__init__.py
opsuite/config/configure.zcml
opsuite/config/initial_globals.txt
opsuite/config/initial_globals_compat.py
opsuite/config/tests.py
opsuite/config/profiles/default/metadata.xml