Metadata-Version: 1.0
Name: opsuite.config
Version: 1.0dev-r12908
Summary: A set of configuration options for all opinion suite projects.
Home-page: about:robots
Author: Matthew Wilkes
Author-email: matt.wilkes@teamrubber.com
License: AGPL
Platform: UNKNOWN
Classifier: Framework :: Plone
Classifier: Programming Language :: Python
Classifier: Topic :: Software Development :: Libraries :: Python Modules
